setup.cfg
setup.py
TelegramBot/__init__.py
TelegramBot/plugin/__init__.py
TelegramBot/plugin/message.py
TelegramBot/service/__init__.py
TelegramBot/service/bot.py
twisted/plugins/telegrambot_plugin.py
txTelegramBot.egg-info/PKG-INFO
txTelegramBot.egg-info/SOURCES.txt
txTelegramBot.egg-info/dependency_links.txt
txTelegramBot.egg-info/requires.txt
txTelegramBot.egg-info/top_level.txt