Metadata-Version: 1.1
Name: txTelegramBot
Version: 0.2
Summary: TelegramBot Service Framework
Home-page: https://github.com/sourcesimian/txTelegramBot
Author: Source Simian
Author-email: sourcesimian@users.noreply.github.com
License: MIT
Download-URL: https://github.com/sourcesimian/txTelegramBot/tarball/v0.2
Platform: UNKNOWN
